{
    "Comment": "None",
    "Name": "C:\\Users\\Juan Pablo Botero T\\OneDrive - Universidad de los Andes\\Documentos\\JPB\\Personal\\Bienestar y Tecnolog\u00eda\\Codigo\\HRV-Bienestar-Tecnologia\\HRV_Reports\\PaulinaPardo_02_12_2021\\HRV_interactive.json",
    "ar_abs": [
        2426.2851258248343,
        4962.1974732723265,
        8926.308441877205
    ],
    "ar_bands": {
        "hf": [
            0.15,
            0.4
        ],
        "lf": [
            0.04,
            0.15
        ],
        "ulf": null,
        "vlf": [
            0.0,
            0.04
        ]
    },
    "ar_interpolation": "cubic",
    "ar_log": [
        7.7941166117920595,
        8.509603960572383,
        9.096758200034404
    ],
    "ar_nfft": 4096.0,
    "ar_norm": [
        35.7288069975877,
        64.2711930024123
    ],
    "ar_order": 16.0,
    "ar_peak": [
        0.0,
        0.0400390625,
        0.150390625
    ],
    "ar_ratio": 0.5559070141462393,
    "ar_rel": [
        14.87168986554136,
        30.41532962824861,
        54.71298050621003
    ],
    "ar_resampling_frequency": 4.0,
    "ar_total": 16314.791040974365,
    "dfa_alpha1": 1.4372864479883742,
    "dfa_alpha1_beats": [
        4,
        5,
        6,
        7,
        8,
        9,
        10,
        11,
        12,
        13,
        14,
        15,
        16
    ],
    "dfa_alpha2": 1.102186109635513,
    "dfa_alpha2_beats": [
        17,
        18,
        19,
        20,
        21,
        22,
        23,
        24,
        25,
        26,
        27,
        28,
        29,
        30,
        31,
        32,
        33,
        34,
        35,
        36,
        37,
        38,
        39,
        40,
        41,
        42,
        43,
        44,
        45,
        46,
        47,
        48,
        49,
        50,
        51,
        52,
        53,
        54,
        55,
        56,
        57,
        58,
        59,
        60,
        61,
        62,
        63,
        64
    ],
    "ellipse_area": 6381.11231098559,
    "fft_abs": [
        900.429856408074,
        807.1819698212802,
        158.75530169301211
    ],
    "fft_bands": {
        "hf": [
            0.15,
            0.4
        ],
        "lf": [
            0.04,
            0.15
        ],
        "ulf": null,
        "vlf": [
            0.0,
            0.04
        ]
    },
    "fft_interpolation": "cubic",
    "fft_log": [
        6.802872267532222,
        6.69354913209677,
        5.067364033706566
    ],
    "fft_nfft": 4096.0,
    "fft_norm": [
        83.56463650645424,
        16.435363493545772
    ],
    "fft_peak": [
        0.0068359375,
        0.0986328125,
        0.380859375
    ],
    "fft_ratio": 5.084441031028633,
    "fft_rel": [
        48.24505548436387,
        43.2488312586084,
        8.506113257027732
    ],
    "fft_resampling_frequency": 4.0,
    "fft_total": 1866.3671279223663,
    "fft_window": "hamming",
    "hr_max": 217.3913043478261,
    "hr_mean": 92.20558735350814,
    "hr_min": 72.90400972053463,
    "hr_std": 9.18596077763247,
    "lomb_abs": [
        227.89877766990645,
        488.9529267219682,
        1320.4859946860981
    ],
    "lomb_bands": {
        "hf": [
            0.15,
            0.4
        ],
        "lf": [
            0.04,
            0.15
        ],
        "ulf": null,
        "vlf": [
            0.0,
            0.04
        ]
    },
    "lomb_log": [
        5.4289015727879635,
        6.192266220468907,
        7.185755125612103
    ],
    "lomb_ma": "n/a",
    "lomb_nfft": 256.0,
    "lomb_norm": [
        27.022350461074176,
        72.97764953892582
    ],
    "lomb_peak": [
        0.00803921568627451,
        0.05305882352941176,
        0.22992156862745097
    ],
    "lomb_ratio": 0.37028255406692184,
    "lomb_rel": [
        11.186107132511482,
        23.99960138877571,
        64.81429147871282
    ],
    "lomb_total": 2037.3376990779727,
    "nn20": 128.0,
    "nn50": 14.0,
    "nni_counter": 367.0,
    "nni_diff_max": 477.0,
    "nni_diff_mean": 19.34153005464481,
    "nni_diff_min": 0.0,
    "nni_max": 823.0,
    "nni_mean": 655.5013623978201,
    "nni_min": 276.0,
    "pnn20": 34.97267759562842,
    "pnn50": 3.825136612021858,
    "rmssd": 42.424571445037394,
    "sampen": 0.9500344801725168,
    "sd1": 29.99675304922804,
    "sd2": 67.71303314403491,
    "sd_ratio": 2.2573454211164194,
    "sdann": "n/a",
    "sdnn": 52.59936600520704,
    "sdnn_index": "n/a",
    "sdsd": 37.810787354830964,
    "tinn": 179.6875,
    "tinn_m": 750.0,
    "tinn_n": 570.3125,
    "tri_index": 11.838709677419354
}