{
    "Comment": "None",
    "Name": "C:\\Users\\admin\\HRV-Bienestar-Tecnologia\\HRV_Reports\\Experiencia_Mindfullness\\16-03-2022_LouisGualtero\\HRV_video.json",
    "ar_abs": [
        2410.6641847781666,
        4936.137568417555,
        8763.312074040005
    ],
    "ar_bands": {
        "hf": [
            0.15,
            0.4
        ],
        "lf": [
            0.04,
            0.15
        ],
        "ulf": null,
        "vlf": [
            0.0,
            0.04
        ]
    },
    "ar_interpolation": "cubic",
    "ar_log": [
        7.787657583858918,
        8.5043384356218,
        9.078329203116017
    ],
    "ar_nfft": 4096.0,
    "ar_norm": [
        36.031648695721294,
        63.968351304278706
    ],
    "ar_order": 16.0,
    "ar_peak": [
        0.0,
        0.0400390625,
        0.150390625
    ],
    "ar_ratio": 0.5632730555197413,
    "ar_rel": [
        14.963669472668172,
        30.639991879340606,
        54.396338647991215
    ],
    "ar_resampling_frequency": 4.0,
    "ar_total": 16110.113827235726,
    "dfa_alpha1": 1.5498160184580771,
    "dfa_alpha1_beats": [
        4,
        5,
        6,
        7,
        8,
        9,
        10,
        11,
        12,
        13,
        14,
        15,
        16
    ],
    "dfa_alpha2": 0.4531689006932177,
    "dfa_alpha2_beats": [
        17,
        18,
        19,
        20,
        21,
        22,
        23,
        24,
        25,
        26,
        27,
        28,
        29,
        30,
        31,
        32,
        33,
        34,
        35,
        36,
        37,
        38,
        39,
        40,
        41,
        42,
        43,
        44,
        45,
        46,
        47,
        48,
        49,
        50,
        51,
        52,
        53,
        54,
        55,
        56,
        57,
        58,
        59,
        60,
        61,
        62,
        63,
        64
    ],
    "ellipse_area": 2536.052864164073,
    "fft_abs": [
        341.73260129781795,
        1241.3123240467978,
        195.05526860775424
    ],
    "fft_bands": {
        "hf": [
            0.15,
            0.4
        ],
        "lf": [
            0.04,
            0.15
        ],
        "ulf": null,
        "vlf": [
            0.0,
            0.04
        ]
    },
    "fft_interpolation": "cubic",
    "fft_log": [
        5.834028563694516,
        7.123924424811292,
        5.273282947163119
    ],
    "fft_nfft": 4096.0,
    "fft_norm": [
        86.42024022226286,
        13.57975977773715
    ],
    "fft_peak": [
        0.0068359375,
        0.0830078125,
        0.19921875
    ],
    "fft_ratio": 6.363900513464268,
    "fft_rel": [
        19.218973287338383,
        69.81115733909249,
        10.969869373569125
    ],
    "fft_resampling_frequency": 4.0,
    "fft_total": 1778.10019395237,
    "fft_window": "hamming",
    "hr_max": 108.499095840868,
    "hr_mean": 87.81781561845584,
    "hr_min": 73.61963190184049,
    "hr_std": 5.471412728540552,
    "lomb_abs": [
        228.0023243164363,
        740.8119529916215,
        1343.727387513472
    ],
    "lomb_bands": {
        "hf": [
            0.15,
            0.4
        ],
        "lf": [
            0.04,
            0.15
        ],
        "ulf": null,
        "vlf": [
            0.0,
            0.04
        ]
    },
    "lomb_log": [
        5.429355823272813,
        6.607746818449667,
        7.203202663837431
    ],
    "lomb_ma": "n/a",
    "lomb_nfft": 256.0,
    "lomb_norm": [
        35.538401151600205,
        64.46159884839979
    ],
    "lomb_peak": [
        0.00803921568627451,
        0.13505882352941176,
        0.3810588235294118
    ],
    "lomb_ratio": 0.5513111959133856,
    "lomb_rel": [
        9.859382331778761,
        32.03453430746268,
        58.10608336075857
    ],
    "lomb_total": 2312.5416648215296,
    "nn20": 101.0,
    "nn50": 5.0,
    "nni_counter": 351.0,
    "nni_diff_max": 69.0,
    "nni_diff_mean": 15.471428571428572,
    "nni_diff_min": 0.0,
    "nni_max": 815.0,
    "nni_mean": 685.8575498575499,
    "nni_min": 553.0,
    "pnn20": 28.857142857142858,
    "pnn50": 1.4285714285714286,
    "rmssd": 19.55643847213203,
    "sampen": 0.984508512654047,
    "sd1": 13.828412189165803,
    "sd2": 58.3762392605423,
    "sd_ratio": 4.221470871853136,
    "sdann": "n/a",
    "sdnn": 42.44044154519459,
    "sdnn_index": "n/a",
    "sdsd": 11.979114380221304,
    "tinn": 187.5,
    "tinn_m": 773.4375,
    "tinn_n": 585.9375,
    "tri_index": 12.10344827586207
}