{
    "Comment": "None",
    "Name": "C:\\Users\\facartesvirtual1\\Documents\\HRV-Bienestar-Tecnologia\\HRV_Reports\\Grupo_Control\\10-03-222_IsabellaAcosta\\Momento_4.json",
    "ar_abs": [
        2464.785190622866,
        5280.469544136782,
        9139.009018688463
    ],
    "ar_bands": {
        "hf": [
            0.15,
            0.4
        ],
        "lf": [
            0.04,
            0.15
        ],
        "ulf": null,
        "vlf": [
            0.0,
            0.04
        ]
    },
    "ar_interpolation": "cubic",
    "ar_log": [
        7.809859938916009,
        8.571770301560159,
        9.120307236107086
    ],
    "ar_nfft": 4096.0,
    "ar_norm": [
        36.620391792462755,
        63.379608207537245
    ],
    "ar_order": 16.0,
    "ar_peak": [
        0.0,
        0.0400390625,
        0.150390625
    ],
    "ar_ratio": 0.5777945435154611,
    "ar_rel": [
        14.598120632411387,
        31.274502822537357,
        54.127376545051256
    ],
    "ar_resampling_frequency": 4.0,
    "ar_total": 16884.26375344811,
    "dfa_alpha1": 1.0385703475368153,
    "dfa_alpha1_beats": [
        4,
        5,
        6,
        7,
        8,
        9,
        10,
        11,
        12,
        13,
        14,
        15,
        16
    ],
    "dfa_alpha2": 0.6221549532843396,
    "dfa_alpha2_beats": [
        17,
        18,
        19,
        20,
        21,
        22,
        23,
        24,
        25,
        26,
        27,
        28,
        29,
        30,
        31,
        32,
        33,
        34,
        35,
        36,
        37,
        38,
        39,
        40,
        41,
        42,
        43,
        44,
        45,
        46,
        47,
        48,
        49,
        50,
        51,
        52,
        53,
        54,
        55,
        56,
        57,
        58,
        59,
        60,
        61,
        62,
        63,
        64
    ],
    "ellipse_area": 8370.846123081608,
    "fft_abs": [
        345.6445576483953,
        1685.1449648092594,
        1463.3693439459787
    ],
    "fft_bands": {
        "hf": [
            0.15,
            0.4
        ],
        "lf": [
            0.04,
            0.15
        ],
        "ulf": null,
        "vlf": [
            0.0,
            0.04
        ]
    },
    "fft_interpolation": "cubic",
    "fft_log": [
        5.845410957000125,
        7.429606871613627,
        7.2884968257174405
    ],
    "fft_nfft": 4096.0,
    "fft_norm": [
        53.521909051621236,
        46.47809094837877
    ],
    "fft_peak": [
        0.009765625,
        0.1494140625,
        0.15625
    ],
    "fft_ratio": 1.1515513645142124,
    "fft_rel": [
        9.892067615235547,
        48.227485619269984,
        41.88044676549447
    ],
    "fft_resampling_frequency": 4.0,
    "fft_total": 3494.1588664036335,
    "fft_window": "hamming",
    "hr_max": 98.84678747940691,
    "hr_mean": 74.29826201342844,
    "hr_min": 63.424947145877375,
    "hr_std": 6.494304397216839,
    "lomb_abs": [
        307.89950360222554,
        595.3614298768155,
        1665.9771751042017
    ],
    "lomb_bands": {
        "hf": [
            0.15,
            0.4
        ],
        "lf": [
            0.04,
            0.15
        ],
        "ulf": null,
        "vlf": [
            0.0,
            0.04
        ]
    },
    "lomb_log": [
        5.7297734427246265,
        6.38916866629661,
        7.418167122215291
    ],
    "lomb_ma": "n/a",
    "lomb_nfft": 256.0,
    "lomb_norm": [
        26.32783204449885,
        73.67216795550115
    ],
    "lomb_peak": [
        0.009647058823529411,
        0.09164705882352941,
        0.36498039215686273
    ],
    "lomb_ratio": 0.3573646978924411,
    "lomb_rel": [
        11.984078181527941,
        23.17268406878474,
        64.84323774968732
    ],
    "lomb_total": 2569.2381085832426,
    "nn20": 190.0,
    "nn50": 66.0,
    "nni_counter": 296.0,
    "nni_diff_max": 146.0,
    "nni_diff_mean": 33.83050847457627,
    "nni_diff_min": 0.0,
    "nni_max": 946.0,
    "nni_mean": 813.3074324324324,
    "nni_min": 607.0,
    "pnn20": 64.40677966101694,
    "pnn50": 22.372881355932204,
    "rmssd": 42.640316722199564,
    "sampen": 1.3629469971228996,
    "sd1": 30.14899741930494,
    "sd2": 88.3784969577128,
    "sd_ratio": 2.931390909242059,
    "sdann": "n/a",
    "sdnn": 66.42964989558244,
    "sdnn_index": "n/a",
    "sdsd": 25.99970731282987,
    "tinn": 265.625,
    "tinn_m": 914.0625,
    "tinn_n": 648.4375,
    "tri_index": 17.41176470588235
}